pymorphy2_dicts_uk/__init__.py
pymorphy2_dicts_uk/version.py
pymorphy2_dicts_uk/data/grammemes.json
pymorphy2_dicts_uk/data/gramtab-opencorpora-ext.json
pymorphy2_dicts_uk/data/gramtab-opencorpora-int.json
pymorphy2_dicts_uk/data/meta.json
pymorphy2_dicts_uk/data/paradigms.array
pymorphy2_dicts_uk/data/prediction-suffixes-0.dawg
pymorphy2_dicts_uk/data/prediction-suffixes-1.dawg
pymorphy2_dicts_uk/data/prediction-suffixes-2.dawg
pymorphy2_dicts_uk/data/prediction-suffixes-3.dawg
pymorphy2_dicts_uk/data/suffixes.json
pymorphy2_dicts_uk/data/words.dawg
pymorphy2_dicts_uk-2.4.1.1.1460299261.dist-info/DESCRIPTION.rst
pymorphy2_dicts_uk-2.4.1.1.1460299261.dist-info/entry_points.txt
pymorphy2_dicts_uk-2.4.1.1.1460299261.dist-info/METADATA
pymorphy2_dicts_uk-2.4.1.1.1460299261.dist-info/metadata.json
pymorphy2_dicts_uk-2.4.1.1.1460299261.dist-info/pbr.json
pymorphy2_dicts_uk-2.4.1.1.1460299261.dist-info/RECORD
pymorphy2_dicts_uk-2.4.1.1.1460299261.dist-info/top_level.txt
pymorphy2_dicts_uk-2.4.1.1.1460299261.dist-info/WHEEL
